swarmzero/__init__.py
swarmzero/agent.py
swarmzero/chat/__init__.py
swarmzero/chat/chat_manager.py
swarmzero/chat/schemas.py
swarmzero/config/__init__.py
swarmzero/config/config.py
swarmzero/database/__init__.py
swarmzero/database/database.py
swarmzero/database/schemas.py
swarmzero/experimental/README.md
swarmzero/experimental/__init__.py
swarmzero/experimental/agent/Dockerfile
swarmzero/experimental/agent/__init__.py
swarmzero/experimental/agent/main.py
swarmzero/experimental/agent/runners/__init__.py
swarmzero/experimental/agent/runners/base_runner.py
swarmzero/experimental/agent/runners/branch_runner.py
swarmzero/experimental/agent/runners/delay_runner.py
swarmzero/experimental/agent/runners/loop_runner.py
swarmzero/experimental/agent/runners/parallel_runner.py
swarmzero/experimental/agent/runners/priority_runner.py
swarmzero/experimental/agent/runners/sequential_runner.py
swarmzero/experimental/agent/tasks/__init__.py
swarmzero/experimental/agent/tasks/task_base.py
swarmzero/experimental/agent/tools.py
swarmzero/experimental/agents.json
swarmzero/experimental/orchestrator/__init__.py
swarmzero/experimental/orchestrator/main.py
swarmzero/experimental/swarmzero-config.example.yaml
swarmzero/filestore/__init__.py
swarmzero/filestore/filestore.py
swarmzero/llms/__init__.py
swarmzero/llms/claude.py
swarmzero/llms/gemini.py
swarmzero/llms/llm.py
swarmzero/llms/mistral.py
swarmzero/llms/nebius.py
swarmzero/llms/ollama.py
swarmzero/llms/openai.py
swarmzero/llms/utils/__init__.py
swarmzero/llms/utils/utils.py
swarmzero/sdk_context.py
swarmzero/server/__init__.py
swarmzero/server/models.py
swarmzero/server/routes/__init__.py
swarmzero/server/routes/chat.py
swarmzero/server/routes/database.py
swarmzero/server/routes/files.py
swarmzero/server/routes/vectorindex.py
swarmzero/swarm.py
swarmzero/tools/__init__.py
swarmzero/tools/agent_db/__init__.py
swarmzero/tools/agent_db/nl_query.py
swarmzero/tools/agent_db/schema.py
swarmzero/tools/retriever/base_retrieve.py
swarmzero-0.0.3.dist-info/LICENSE
swarmzero-0.0.3.dist-info/METADATA
swarmzero-0.0.3.dist-info/WHEEL
swarmzero-0.0.3.dist-info/RECORD
