Metadata-Version: 2.1
Name: swarmzero
Version: 0.0.3
Summary: This library provides you with an easy way to orchestrate AI Agents and Swarms on SwarmZero
Home-page: https://swarmzero.ai
Author: SwarmZero Team
Author-email: info@swarmzero.ai
Requires-Python: >=3.11,<3.13
Classifier: Programming Language :: Python :: 3
Classifier: Programming Language :: Python :: 3.11
Classifier: Programming Language :: Python :: 3.12
Provides-Extra: web3
Requires-Dist: SQLAlchemy (==2.0.36)
Requires-Dist: aiosqlite (==0.20.0)
Requires-Dist: asyncpg (>=0.30.0,<0.31.0)
Requires-Dist: boto3 (>=1.34.27,<2.0.0)
Requires-Dist: chromadb (==0.5.23)
Requires-Dist: colorama (>=0.4.6,<0.5.0)
Requires-Dist: docx2txt (==0.8)
Requires-Dist: fastapi (==0.115.6)
Requires-Dist: langtrace-python-sdk (==3.3.14)
Requires-Dist: llama-index (==0.12.8)
Requires-Dist: llama-index-llms-anthropic (==0.6.3)
Requires-Dist: llama-index-llms-azure-openai (==0.3.0)
Requires-Dist: llama-index-llms-gemini (==0.4.2)
Requires-Dist: llama-index-llms-mistralai (==0.3.1)
Requires-Dist: llama-index-llms-nebius (>=0.1.1,<0.2.0)
Requires-Dist: llama-index-llms-ollama (==0.5.0)
Requires-Dist: llama-index-llms-openai (==0.3.12)
Requires-Dist: llama-index-multi-modal-llms-openai (==0.4.1)
Requires-Dist: llama-index-readers-s3 (==0.4.0)
Requires-Dist: llama-index-vector-stores-chroma (==0.4.1)
Requires-Dist: llama-index-vector-stores-pinecone (==0.4.2)
Requires-Dist: openlit (>=1.33.1,<2.0.0)
Requires-Dist: openpyxl (==3.1.5)
Requires-Dist: python-dotenv (==1.0.1)
Requires-Dist: python-multipart (==0.0.19)
Requires-Dist: redis (>=5.2.1,<6.0.0)
Requires-Dist: requests (==2.32.3)
Requires-Dist: toml (==0.10.2)
Requires-Dist: types-boto3 (>=1.0.2,<2.0.0)
Requires-Dist: uvicorn (==0.32.1)
Requires-Dist: xlrd (==2.0.1)
Project-URL: Repository, https://github.com/swarmzero/swarmzero
